zync/__init__.py
zync/logger.py
zync/main.py
zync/slugify.py
zyncify-0.1.9.dist-info/LICENSE
zyncify-0.1.9.dist-info/METADATA
zyncify-0.1.9.dist-info/WHEEL
zyncify-0.1.9.dist-info/entry_points.txt
zyncify-0.1.9.dist-info/top_level.txt
zyncify-0.1.9.dist-info/RECORD
