Metadata-Version: 2.1
Name: zyncify
Version: 0.1.9
Summary: zync is a utility tool for python operations
Home-page: https://github.com/tjbredemeyer/zync
Author: TJ Bredemeyer
Author-email: tj@teicor.com
License: GNU Public License v3
License-File: LICENSE
